bit_counter-0.3.1.dist-info/METADATA
bit_counter-0.3.1.dist-info/WHEEL
bit_counter-0.3.1.dist-info/licenses/LICENSE.md
bit_counter/__init__.py
bit_counter/bit_counter.cp311-win32.pyd
bit_counter-0.3.1.dist-info/RECORD
