Metadata-Version: 2.4
Name: bit-counter
Version: 0.3.1
Classifier: Programming Language :: Rust
Classifier: Programming Language :: Python :: Implementation :: CPython
Classifier: Programming Language :: Python :: Implementation :: PyPy
License-File: LICENSE.md
Summary: Package for efficiently counting the number of one bits in a numpy array.
Requires-Python: >=3.7
